deleo/__init__.py
deleo/__main__.py
deleo/recovery.py
deleo/restore.py
deleo-0.1.dist-info/LICENSE
deleo-0.1.dist-info/METADATA
deleo-0.1.dist-info/WHEEL
deleo-0.1.dist-info/entry_points.txt
deleo-0.1.dist-info/RECORD
