Metadata-Version: 2.1
Name: deleo
Version: 0.1
Summary: A Python CLI tool for downgrading i(Pad)OS devices.
Home-page: https://github.com/m1stadev/deleo
License: MIT
Author: m1stadev
Author-email: adamhamdi31@gmail.com
Requires-Python: >=3.8,<4.0
Classifier: License :: OSI Approved :: MIT License
Classifier: Programming Language :: Python :: 3
Classifier: Programming Language :: Python :: 3.8
Classifier: Programming Language :: Python :: 3.9
Classifier: Programming Language :: Python :: 3.10
Classifier: Programming Language :: Python :: 3.11
Classifier: Programming Language :: Python :: 3.12
Requires-Dist: click (>=8.1.6,<9.0.0)
Requires-Dist: coloredlogs (>=15.0.1,<16.0.0)
Requires-Dist: ipsw-parser (>=1.1.5,<2.0.0)
Requires-Dist: pymobiledevice3 (==2.34.0)
Requires-Dist: remotezip (>=0.12.1,<0.13.0)
Requires-Dist: tqdm (>=4.65.0,<5.0.0)
Project-URL: Bug Tracker, https://github.com/m1stadev/deleo/issues
Project-URL: Repository, https://github.com/m1stadev/deleo
